[
    {
        "filename": "/tmp/block-diagonal/38000-22.mtx",
        "problem": {
            "collection": "generated",
            "group": "block-diagonal",
            "name": "38000-22",
            "type": "block-diagonal",
            "real": true,
            "binary": false,
            "2d3d": false,
            "posdef": false,
            "psym": 1,
            "nsym": 0,
            "kind": "artificially generated problem",
            "num_blocks": 38000,
            "block_size": 22,
            "row_distribution": {
                "min": 22,
                "q1": 22.0,
                "median": 22.0,
                "q3": 22.0,
                "max": 22,
                "mean": 22.0,
                "variance": 0.0,
                "skewness": 0.0,
                "kurtosis": 0.0,
                "hyperskewness": 0.0,
                "hyperflatness": 0.0
            },
            "col_distribution": {
                "min": 22,
                "q1": 22.0,
                "median": 22.0,
                "q3": 22.0,
                "max": 22,
                "mean": 22.0,
                "variance": 0.0,
                "skewness": 0.0,
                "kurtosis": 0.0,
                "hyperskewness": 0.0,
                "hyperflatness": 0.0
            }
        },
        "preconditioner": {
            "jacobi-1": {
                "generate": {
                    "components": {
                        "find_blocks": 408689265,
                        "generate": 666879
                    },
                    "time": 410367344
                },
                "apply": {
                    "components": {
                        "simple_apply": 54454
                    },
                    "time": 48372
                },
                "completed": true
            },
            "jacobi-2": {
                "generate": {
                    "components": {
                        "find_blocks": 236774692,
                        "generate": 632495
                    },
                    "time": 238815725
                },
                "apply": {
                    "components": {
                        "simple_apply": 66290
                    },
                    "time": 59851
                },
                "completed": true
            },
            "jacobi-3": {
                "generate": {
                    "components": {
                        "find_blocks": 185943739,
                        "generate": 708829
                    },
                    "time": 188062714
                },
                "apply": {
                    "components": {
                        "simple_apply": 81382
                    },
                    "time": 74717
                },
                "completed": true
            },
            "jacobi-4": {
                "generate": {
                    "components": {
                        "find_blocks": 158454880,
                        "generate": 739192
                    },
                    "time": 160958902
                },
                "apply": {
                    "components": {
                        "simple_apply": 94965
                    },
                    "time": 88690
                },
                "completed": true
            },
            "jacobi-5": {
                "generate": {
                    "components": {
                        "find_blocks": 142339256,
                        "generate": 1018673
                    },
                    "time": 145270285
                },
                "apply": {
                    "components": {
                        "simple_apply": 111561
                    },
                    "time": 104653
                },
                "completed": true
            },
            "jacobi-6": {
                "generate": {
                    "components": {
                        "find_blocks": 128200355,
                        "generate": 1011393
                    },
                    "time": 131456845
                },
                "apply": {
                    "components": {
                        "simple_apply": 122306
                    },
                    "time": 115455
                },
                "completed": true
            },
            "jacobi-7": {
                "generate": {
                    "components": {
                        "find_blocks": 126839933,
                        "generate": 1105636
                    },
                    "time": 130413233
                },
                "apply": {
                    "components": {
                        "simple_apply": 133483
                    },
                    "time": 127632
                },
                "completed": true
            },
            "jacobi-8": {
                "generate": {
                    "components": {
                        "find_blocks": 113093119,
                        "generate": 1149091
                    },
                    "time": 117248534
                },
                "apply": {
                    "components": {
                        "simple_apply": 135343
                    },
                    "time": 129310
                },
                "completed": true
            },
            "jacobi-9": {
                "generate": {
                    "components": {
                        "find_blocks": 112308996,
                        "generate": 1773238
                    },
                    "time": 117033111
                },
                "apply": {
                    "components": {
                        "simple_apply": 165790
                    },
                    "time": 159995
                },
                "completed": true
            },
            "jacobi-10": {
                "generate": {
                    "components": {
                        "find_blocks": 113066589,
                        "generate": 2067732
                    },
                    "time": 118281662
                },
                "apply": {
                    "components": {
                        "simple_apply": 182624
                    },
                    "time": 175769
                },
                "completed": true
            },
            "jacobi-11": {
                "generate": {
                    "components": {
                        "find_blocks": 97231226,
                        "generate": 1632137
                    },
                    "time": 102335302
                },
                "apply": {
                    "components": {
                        "simple_apply": 178171
                    },
                    "time": 172348
                },
                "completed": true
            },
            "jacobi-12": {
                "generate": {
                    "components": {
                        "find_blocks": 98087971,
                        "generate": 1740940
                    },
                    "time": 103663151
                },
                "apply": {
                    "components": {
                        "simple_apply": 188881
                    },
                    "time": 182428
                },
                "completed": true
            },
            "jacobi-13": {
                "generate": {
                    "components": {
                        "find_blocks": 97258741,
                        "generate": 1892072
                    },
                    "time": 103071160
                },
                "apply": {
                    "components": {
                        "simple_apply": 199985
                    },
                    "time": 193731
                },
                "completed": true
            },
            "jacobi-14": {
                "generate": {
                    "components": {
                        "find_blocks": 98089891,
                        "generate": 2064965
                    },
                    "time": 104312497
                },
                "apply": {
                    "components": {
                        "simple_apply": 205799
                    },
                    "time": 199298
                },
                "completed": true
            },
            "jacobi-15": {
                "generate": {
                    "components": {
                        "find_blocks": 97227754,
                        "generate": 2189804
                    },
                    "time": 103667276
                },
                "apply": {
                    "components": {
                        "simple_apply": 218778
                    },
                    "time": 212132
                },
                "completed": true
            },
            "jacobi-16": {
                "generate": {
                    "components": {
                        "find_blocks": 98003597,
                        "generate": 2307211
                    },
                    "time": 105312269
                },
                "apply": {
                    "components": {
                        "simple_apply": 213828
                    },
                    "time": 208325
                },
                "completed": true
            },
            "jacobi-17": {
                "generate": {
                    "components": {
                        "find_blocks": 97262207,
                        "generate": 3089255
                    },
                    "time": 104910141
                },
                "apply": {
                    "components": {
                        "simple_apply": 283531
                    },
                    "time": 276903
                },
                "completed": true
            },
            "jacobi-18": {
                "generate": {
                    "components": {
                        "find_blocks": 98082444,
                        "generate": 3211860
                    },
                    "time": 106085346
                },
                "apply": {
                    "components": {
                        "simple_apply": 293500
                    },
                    "time": 287761
                },
                "completed": true
            },
            "jacobi-19": {
                "generate": {
                    "components": {
                        "find_blocks": 97244011,
                        "generate": 3197173
                    },
                    "time": 105395240
                },
                "apply": {
                    "components": {
                        "simple_apply": 320924
                    },
                    "time": 315689
                },
                "completed": true
            },
            "jacobi-20": {
                "generate": {
                    "components": {
                        "find_blocks": 98093149,
                        "generate": 3323148
                    },
                    "time": 106899316
                },
                "apply": {
                    "components": {
                        "simple_apply": 328214
                    },
                    "time": 322242
                },
                "completed": true
            },
            "jacobi-21": {
                "generate": {
                    "components": {
                        "find_blocks": 97318498,
                        "generate": 3568041
                    },
                    "time": 106064441
                },
                "apply": {
                    "components": {
                        "simple_apply": 343068
                    },
                    "time": 338861
                },
                "completed": true
            },
            "jacobi-22": {
                "generate": {
                    "components": {
                        "find_blocks": 83144435,
                        "generate": 3547841
                    },
                    "time": 92071654
                },
                "apply": {
                    "components": {
                        "simple_apply": 329260
                    },
                    "time": 326397
                },
                "completed": true
            },
            "jacobi-23": {
                "generate": {
                    "components": {
                        "find_blocks": 83145512,
                        "generate": 3654978
                    },
                    "time": 92456446
                },
                "apply": {
                    "components": {
                        "simple_apply": 350670
                    },
                    "time": 346988
                },
                "completed": true
            },
            "jacobi-24": {
                "generate": {
                    "components": {
                        "find_blocks": 83148950,
                        "generate": 4113078
                    },
                    "time": 93852676
                },
                "apply": {
                    "components": {
                        "simple_apply": 410457
                    },
                    "time": 401857
                },
                "completed": true
            },
            "jacobi-25": {
                "generate": {
                    "components": {
                        "find_blocks": 83150098,
                        "generate": 4112842
                    },
                    "time": 93475055
                },
                "apply": {
                    "components": {
                        "simple_apply": 361716
                    },
                    "time": 359315
                },
                "completed": true
            },
            "jacobi-26": {
                "generate": {
                    "components": {
                        "find_blocks": 83148238,
                        "generate": 4166897
                    },
                    "time": 93986810
                },
                "apply": {
                    "components": {
                        "simple_apply": 332361
                    },
                    "time": 326109
                },
                "completed": true
            },
            "jacobi-27": {
                "generate": {
                    "components": {
                        "find_blocks": 83152312,
                        "generate": 4015333
                    },
                    "time": 94113499
                },
                "apply": {
                    "components": {
                        "simple_apply": 337936
                    },
                    "time": 331765
                },
                "completed": true
            },
            "jacobi-28": {
                "generate": {
                    "components": {
                        "find_blocks": 83146358,
                        "generate": 4384758
                    },
                    "time": 95187669
                },
                "apply": {
                    "components": {
                        "simple_apply": 331452
                    },
                    "time": 324819
                },
                "completed": true
            },
            "jacobi-29": {
                "generate": {
                    "components": {
                        "find_blocks": 83152850,
                        "generate": 4291456
                    },
                    "time": 94809708
                },
                "apply": {
                    "components": {
                        "simple_apply": 343674
                    },
                    "time": 336858
                },
                "completed": true
            },
            "jacobi-30": {
                "generate": {
                    "components": {
                        "find_blocks": 83232684,
                        "generate": 4342682
                    },
                    "time": 94829807
                },
                "apply": {
                    "components": {
                        "simple_apply": 405219
                    },
                    "time": 401933
                },
                "completed": true
            },
            "jacobi-31": {
                "generate": {
                    "components": {
                        "find_blocks": 83154999,
                        "generate": 4359584
                    },
                    "time": 95167265
                },
                "apply": {
                    "components": {
                        "simple_apply": 365078
                    },
                    "time": 359897
                },
                "completed": true
            },
            "jacobi-32": {
                "generate": {
                    "components": {
                        "find_blocks": 83151785,
                        "generate": 4332418
                    },
                    "time": 95742497
                },
                "apply": {
                    "components": {
                        "simple_apply": 337564
                    },
                    "time": 332039
                },
                "completed": true
            }
        }
    }
]