[
    {
        "filename": "/tmp/block-diagonal/40000-2.mtx",
        "problem": {
            "collection": "generated",
            "group": "block-diagonal",
            "name": "40000-2",
            "type": "block-diagonal",
            "real": true,
            "binary": false,
            "2d3d": false,
            "posdef": false,
            "psym": 1,
            "nsym": 0,
            "kind": "artificially generated problem",
            "num_blocks": 40000,
            "block_size": 2,
            "row_distribution": {
                "min": 2,
                "q1": 2.0,
                "median": 2.0,
                "q3": 2.0,
                "max": 2,
                "mean": 2.0,
                "variance": 0.0,
                "skewness": 0.0,
                "kurtosis": 0.0,
                "hyperskewness": 0.0,
                "hyperflatness": 0.0
            },
            "col_distribution": {
                "min": 2,
                "q1": 2.0,
                "median": 2.0,
                "q3": 2.0,
                "max": 2,
                "mean": 2.0,
                "variance": 0.0,
                "skewness": 0.0,
                "kurtosis": 0.0,
                "hyperskewness": 0.0,
                "hyperflatness": 0.0
            }
        },
        "preconditioner": {
            "jacobi-1": {
                "generate": {
                    "components": {
                        "find_blocks": 41799037,
                        "generate": 80869
                    },
                    "time": 41843398
                },
                "apply": {
                    "components": {
                        "simple_apply": 11626
                    },
                    "time": 4639
                },
                "completed": true
            },
            "jacobi-2": {
                "generate": {
                    "components": {
                        "find_blocks": 24984759,
                        "generate": 73957
                    },
                    "time": 25004714
                },
                "apply": {
                    "components": {
                        "simple_apply": 12237
                    },
                    "time": 5824
                },
                "completed": true
            },
            "jacobi-3": {
                "generate": {
                    "components": {
                        "find_blocks": 24741383,
                        "generate": 80980
                    },
                    "time": 25322501
                },
                "apply": {
                    "components": {
                        "simple_apply": 15182
                    },
                    "time": 8043
                },
                "completed": true
            },
            "jacobi-4": {
                "generate": {
                    "components": {
                        "find_blocks": 20448746,
                        "generate": 76399
                    },
                    "time": 20954211
                },
                "apply": {
                    "components": {
                        "simple_apply": 16866
                    },
                    "time": 10390
                },
                "completed": true
            },
            "jacobi-5": {
                "generate": {
                    "components": {
                        "find_blocks": 20453619,
                        "generate": 99950
                    },
                    "time": 20976535
                },
                "apply": {
                    "components": {
                        "simple_apply": 21206
                    },
                    "time": 15321
                },
                "completed": true
            },
            "jacobi-6": {
                "generate": {
                    "components": {
                        "find_blocks": 20382259,
                        "generate": 114991
                    },
                    "time": 20978885
                },
                "apply": {
                    "components": {
                        "simple_apply": 21783
                    },
                    "time": 15784
                },
                "completed": true
            },
            "jacobi-7": {
                "generate": {
                    "components": {
                        "find_blocks": 20464118,
                        "generate": 115705
                    },
                    "time": 21008262
                },
                "apply": {
                    "components": {
                        "simple_apply": 23666
                    },
                    "time": 17793
                },
                "completed": true
            },
            "jacobi-8": {
                "generate": {
                    "components": {
                        "find_blocks": 20453795,
                        "generate": 123814
                    },
                    "time": 20985356
                },
                "apply": {
                    "components": {
                        "simple_apply": 23025
                    },
                    "time": 16980
                },
                "completed": true
            },
            "jacobi-9": {
                "generate": {
                    "components": {
                        "find_blocks": 20423655,
                        "generate": 161484
                    },
                    "time": 21042964
                },
                "apply": {
                    "components": {
                        "simple_apply": 30248
                    },
                    "time": 24160
                },
                "completed": true
            },
            "jacobi-10": {
                "generate": {
                    "components": {
                        "find_blocks": 20466581,
                        "generate": 163672
                    },
                    "time": 21079483
                },
                "apply": {
                    "components": {
                        "simple_apply": 31854
                    },
                    "time": 26259
                },
                "completed": true
            },
            "jacobi-11": {
                "generate": {
                    "components": {
                        "find_blocks": 20454539,
                        "generate": 169544
                    },
                    "time": 21064257
                },
                "apply": {
                    "components": {
                        "simple_apply": 32478
                    },
                    "time": 27084
                },
                "completed": true
            },
            "jacobi-12": {
                "generate": {
                    "components": {
                        "find_blocks": 20440461,
                        "generate": 177553
                    },
                    "time": 21084543
                },
                "apply": {
                    "components": {
                        "simple_apply": 30259
                    },
                    "time": 24651
                },
                "completed": true
            },
            "jacobi-13": {
                "generate": {
                    "components": {
                        "find_blocks": 20373876,
                        "generate": 186072
                    },
                    "time": 21103713
                },
                "apply": {
                    "components": {
                        "simple_apply": 30549
                    },
                    "time": 25720
                },
                "completed": true
            },
            "jacobi-14": {
                "generate": {
                    "components": {
                        "find_blocks": 20477523,
                        "generate": 197586
                    },
                    "time": 21191157
                },
                "apply": {
                    "components": {
                        "simple_apply": 32338
                    },
                    "time": 26752
                },
                "completed": true
            },
            "jacobi-15": {
                "generate": {
                    "components": {
                        "find_blocks": 20469195,
                        "generate": 201568
                    },
                    "time": 21193888
                },
                "apply": {
                    "components": {
                        "simple_apply": 33156
                    },
                    "time": 27351
                },
                "completed": true
            },
            "jacobi-16": {
                "generate": {
                    "components": {
                        "find_blocks": 20368793,
                        "generate": 187548
                    },
                    "time": 21166568
                },
                "apply": {
                    "components": {
                        "simple_apply": 33940
                    },
                    "time": 28485
                },
                "completed": true
            },
            "jacobi-17": {
                "generate": {
                    "components": {
                        "find_blocks": 20469591,
                        "generate": 333117
                    },
                    "time": 21365011
                },
                "apply": {
                    "components": {
                        "simple_apply": 45815
                    },
                    "time": 40431
                },
                "completed": true
            },
            "jacobi-18": {
                "generate": {
                    "components": {
                        "find_blocks": 20465369,
                        "generate": 328650
                    },
                    "time": 21370118
                },
                "apply": {
                    "components": {
                        "simple_apply": 47978
                    },
                    "time": 42959
                },
                "completed": true
            },
            "jacobi-19": {
                "generate": {
                    "components": {
                        "find_blocks": 20444290,
                        "generate": 323748
                    },
                    "time": 21366686
                },
                "apply": {
                    "components": {
                        "simple_apply": 50712
                    },
                    "time": 46474
                },
                "completed": true
            },
            "jacobi-20": {
                "generate": {
                    "components": {
                        "find_blocks": 20467771,
                        "generate": 336558
                    },
                    "time": 21453436
                },
                "apply": {
                    "components": {
                        "simple_apply": 53894
                    },
                    "time": 49979
                },
                "completed": true
            },
            "jacobi-21": {
                "generate": {
                    "components": {
                        "find_blocks": 20468075,
                        "generate": 358460
                    },
                    "time": 21471993
                },
                "apply": {
                    "components": {
                        "simple_apply": 54703
                    },
                    "time": 50475
                },
                "completed": true
            },
            "jacobi-22": {
                "generate": {
                    "components": {
                        "find_blocks": 20438682,
                        "generate": 359555
                    },
                    "time": 21464079
                },
                "apply": {
                    "components": {
                        "simple_apply": 56492
                    },
                    "time": 52032
                },
                "completed": true
            },
            "jacobi-23": {
                "generate": {
                    "components": {
                        "find_blocks": 20472150,
                        "generate": 381914
                    },
                    "time": 21546424
                },
                "apply": {
                    "components": {
                        "simple_apply": 58320
                    },
                    "time": 53690
                },
                "completed": true
            },
            "jacobi-24": {
                "generate": {
                    "components": {
                        "find_blocks": 20466245,
                        "generate": 406828
                    },
                    "time": 21573822
                },
                "apply": {
                    "components": {
                        "simple_apply": 49624
                    },
                    "time": 43933
                },
                "completed": true
            },
            "jacobi-25": {
                "generate": {
                    "components": {
                        "find_blocks": 20468834,
                        "generate": 392919
                    },
                    "time": 21563730
                },
                "apply": {
                    "components": {
                        "simple_apply": 50841
                    },
                    "time": 45839
                },
                "completed": true
            },
            "jacobi-26": {
                "generate": {
                    "components": {
                        "find_blocks": 20379386,
                        "generate": 419036
                    },
                    "time": 21577311
                },
                "apply": {
                    "components": {
                        "simple_apply": 55194
                    },
                    "time": 50485
                },
                "completed": true
            },
            "jacobi-27": {
                "generate": {
                    "components": {
                        "find_blocks": 20470904,
                        "generate": 431125
                    },
                    "time": 21658486
                },
                "apply": {
                    "components": {
                        "simple_apply": 54719
                    },
                    "time": 49240
                },
                "completed": true
            },
            "jacobi-28": {
                "generate": {
                    "components": {
                        "find_blocks": 20474652,
                        "generate": 465120
                    },
                    "time": 21705382
                },
                "apply": {
                    "components": {
                        "simple_apply": 56049
                    },
                    "time": 50546
                },
                "completed": true
            },
            "jacobi-29": {
                "generate": {
                    "components": {
                        "find_blocks": 20379325,
                        "generate": 448220
                    },
                    "time": 21675035
                },
                "apply": {
                    "components": {
                        "simple_apply": 55844
                    },
                    "time": 51071
                },
                "completed": true
            },
            "jacobi-30": {
                "generate": {
                    "components": {
                        "find_blocks": 20474036,
                        "generate": 458911
                    },
                    "time": 21760834
                },
                "apply": {
                    "components": {
                        "simple_apply": 57543
                    },
                    "time": 52463
                },
                "completed": true
            },
            "jacobi-31": {
                "generate": {
                    "components": {
                        "find_blocks": 20470274,
                        "generate": 472066
                    },
                    "time": 21772797
                },
                "apply": {
                    "components": {
                        "simple_apply": 59159
                    },
                    "time": 54067
                },
                "completed": true
            },
            "jacobi-32": {
                "generate": {
                    "components": {
                        "find_blocks": 20461518,
                        "generate": 447219
                    },
                    "time": 21787126
                },
                "apply": {
                    "components": {
                        "simple_apply": 57052
                    },
                    "time": 52179
                },
                "completed": true
            }
        }
    }
]