[
    {
        "filename": "/tmp/block-diagonal/44000-16.mtx",
        "problem": {
            "collection": "generated",
            "group": "block-diagonal",
            "name": "44000-16",
            "type": "block-diagonal",
            "real": true,
            "binary": false,
            "2d3d": false,
            "posdef": false,
            "psym": 1,
            "nsym": 0,
            "kind": "artificially generated problem",
            "num_blocks": 44000,
            "block_size": 16,
            "row_distribution": {
                "min": 16,
                "q1": 16.0,
                "median": 16.0,
                "q3": 16.0,
                "max": 16,
                "mean": 16.0,
                "variance": 0.0,
                "skewness": 0.0,
                "kurtosis": 0.0,
                "hyperskewness": 0.0,
                "hyperflatness": 0.0
            },
            "col_distribution": {
                "min": 16,
                "q1": 16.0,
                "median": 16.0,
                "q3": 16.0,
                "max": 16,
                "mean": 16.0,
                "variance": 0.0,
                "skewness": 0.0,
                "kurtosis": 0.0,
                "hyperskewness": 0.0,
                "hyperflatness": 0.0
            }
        },
        "preconditioner": {
            "jacobi-16-0,0": {
                "generate": {
                    "components": {
                        "find_blocks": 33701868,
                        "generate": 1324876
                    },
                    "time": 37850768
                },
                "apply": {
                    "components": {
                        "simple_apply": 150275
                    },
                    "time": 140704
                },
                "completed": true
            },
            "jacobi-16-0,1": {
                "generate": {
                    "components": {
                        "find_blocks": 33697619,
                        "generate": 1217276,
                        "initialize_precisions": 14972
                    },
                    "time": 36699542
                },
                "apply": {
                    "components": {
                        "simple_apply": 98131
                    },
                    "time": 86956
                },
                "completed": true
            },
            "jacobi-16-0,2": {
                "generate": {
                    "components": {
                        "find_blocks": 33700706,
                        "generate": 1139493,
                        "initialize_precisions": 14981
                    },
                    "time": 36623555
                },
                "apply": {
                    "components": {
                        "simple_apply": 87573
                    },
                    "time": 77973
                },
                "completed": true
            },
            "jacobi-16-1,0": {
                "generate": {
                    "components": {
                        "find_blocks": 33703824,
                        "generate": 1221840,
                        "initialize_precisions": 14712
                    },
                    "time": 36699758
                },
                "apply": {
                    "components": {
                        "simple_apply": 97946
                    },
                    "time": 87219
                },
                "completed": true
            },
            "jacobi-16-1,1": {
                "generate": {
                    "components": {
                        "find_blocks": 33700380,
                        "generate": 1140137,
                        "initialize_precisions": 14839
                    },
                    "time": 36621050
                },
                "apply": {
                    "components": {
                        "simple_apply": 87168
                    },
                    "time": 77426
                },
                "completed": true
            },
            "jacobi-16-2,0": {
                "generate": {
                    "components": {
                        "find_blocks": 33702563,
                        "generate": 1143851,
                        "initialize_precisions": 14704
                    },
                    "time": 37679707
                },
                "apply": {
                    "components": {
                        "simple_apply": 87593
                    },
                    "time": 77559
                },
                "completed": true
            },
            "jacobi-16-autodetect": {
                "generate": {
                    "components": {
                        "find_blocks": 33704151,
                        "generate": 2016267,
                        "initialize_precisions": 14833
                    },
                    "time": 37495212
                },
                "apply": {
                    "components": {
                        "simple_apply": 97872
                    },
                    "time": 86892
                },
                "completed": true
            }
        }
    }
]