[
    {
        "filename": "/tmp/block-diagonal/36000-2.mtx",
        "problem": {
            "collection": "generated",
            "group": "block-diagonal",
            "name": "36000-2",
            "type": "block-diagonal",
            "real": true,
            "binary": false,
            "2d3d": false,
            "posdef": false,
            "psym": 1,
            "nsym": 0,
            "kind": "artificially generated problem",
            "num_blocks": 36000,
            "block_size": 2,
            "row_distribution": {
                "min": 2,
                "q1": 2.0,
                "median": 2.0,
                "q3": 2.0,
                "max": 2,
                "mean": 2.0,
                "variance": 0.0,
                "skewness": 0.0,
                "kurtosis": 0.0,
                "hyperskewness": 0.0,
                "hyperflatness": 0.0
            },
            "col_distribution": {
                "min": 2,
                "q1": 2.0,
                "median": 2.0,
                "q3": 2.0,
                "max": 2,
                "mean": 2.0,
                "variance": 0.0,
                "skewness": 0.0,
                "kurtosis": 0.0,
                "hyperskewness": 0.0,
                "hyperflatness": 0.0
            }
        },
        "preconditioner": {
            "jacobi-1": {
                "generate": {
                    "components": {
                        "find_blocks": 36151655,
                        "generate": 78720
                    },
                    "time": 36196113
                },
                "apply": {
                    "components": {
                        "simple_apply": 12579
                    },
                    "time": 5648
                },
                "completed": true
            },
            "jacobi-2": {
                "generate": {
                    "components": {
                        "find_blocks": 21684816,
                        "generate": 71836
                    },
                    "time": 21853254
                },
                "apply": {
                    "components": {
                        "simple_apply": 13044
                    },
                    "time": 6689
                },
                "completed": true
            },
            "jacobi-3": {
                "generate": {
                    "components": {
                        "find_blocks": 21785895,
                        "generate": 80804
                    },
                    "time": 22274382
                },
                "apply": {
                    "components": {
                        "simple_apply": 17522
                    },
                    "time": 10676
                },
                "completed": true
            },
            "jacobi-4": {
                "generate": {
                    "components": {
                        "find_blocks": 18074972,
                        "generate": 85061
                    },
                    "time": 18557779
                },
                "apply": {
                    "components": {
                        "simple_apply": 15466
                    },
                    "time": 8378
                },
                "completed": true
            },
            "jacobi-5": {
                "generate": {
                    "components": {
                        "find_blocks": 18063932,
                        "generate": 97640
                    },
                    "time": 18572465
                },
                "apply": {
                    "components": {
                        "simple_apply": 19747
                    },
                    "time": 13865
                },
                "completed": true
            },
            "jacobi-6": {
                "generate": {
                    "components": {
                        "find_blocks": 18059984,
                        "generate": 119266
                    },
                    "time": 18590764
                },
                "apply": {
                    "components": {
                        "simple_apply": 22580
                    },
                    "time": 16910
                },
                "completed": true
            },
            "jacobi-7": {
                "generate": {
                    "components": {
                        "find_blocks": 18053346,
                        "generate": 115994
                    },
                    "time": 18571377
                },
                "apply": {
                    "components": {
                        "simple_apply": 23112
                    },
                    "time": 16884
                },
                "completed": true
            },
            "jacobi-8": {
                "generate": {
                    "components": {
                        "find_blocks": 18069072,
                        "generate": 139985
                    },
                    "time": 18615758
                },
                "apply": {
                    "components": {
                        "simple_apply": 22304
                    },
                    "time": 17487
                },
                "completed": true
            },
            "jacobi-9": {
                "generate": {
                    "components": {
                        "find_blocks": 18080541,
                        "generate": 158356
                    },
                    "time": 18743242
                },
                "apply": {
                    "components": {
                        "simple_apply": 26847
                    },
                    "time": 20836
                },
                "completed": true
            },
            "jacobi-10": {
                "generate": {
                    "components": {
                        "find_blocks": 18084817,
                        "generate": 169022
                    },
                    "time": 18711557
                },
                "apply": {
                    "components": {
                        "simple_apply": 30235
                    },
                    "time": 24447
                },
                "completed": true
            },
            "jacobi-11": {
                "generate": {
                    "components": {
                        "find_blocks": 18080890,
                        "generate": 171673
                    },
                    "time": 18707361
                },
                "apply": {
                    "components": {
                        "simple_apply": 29859
                    },
                    "time": 25417
                },
                "completed": true
            },
            "jacobi-12": {
                "generate": {
                    "components": {
                        "find_blocks": 18064730,
                        "generate": 177924
                    },
                    "time": 18682496
                },
                "apply": {
                    "components": {
                        "simple_apply": 27304
                    },
                    "time": 22107
                },
                "completed": true
            },
            "jacobi-13": {
                "generate": {
                    "components": {
                        "find_blocks": 18041010,
                        "generate": 189171
                    },
                    "time": 18672601
                },
                "apply": {
                    "components": {
                        "simple_apply": 27644
                    },
                    "time": 22359
                },
                "completed": true
            },
            "jacobi-14": {
                "generate": {
                    "components": {
                        "find_blocks": 18034593,
                        "generate": 206600
                    },
                    "time": 18677582
                },
                "apply": {
                    "components": {
                        "simple_apply": 31195
                    },
                    "time": 25884
                },
                "completed": true
            },
            "jacobi-15": {
                "generate": {
                    "components": {
                        "find_blocks": 18049394,
                        "generate": 208993
                    },
                    "time": 18690895
                },
                "apply": {
                    "components": {
                        "simple_apply": 31333
                    },
                    "time": 26040
                },
                "completed": true
            },
            "jacobi-16": {
                "generate": {
                    "components": {
                        "find_blocks": 18079584,
                        "generate": 242611
                    },
                    "time": 18768654
                },
                "apply": {
                    "components": {
                        "simple_apply": 30813
                    },
                    "time": 25804
                },
                "completed": true
            },
            "jacobi-17": {
                "generate": {
                    "components": {
                        "find_blocks": 18321060,
                        "generate": 340030
                    },
                    "time": 19162921
                },
                "apply": {
                    "components": {
                        "simple_apply": 38141
                    },
                    "time": 32383
                },
                "completed": true
            },
            "jacobi-18": {
                "generate": {
                    "components": {
                        "find_blocks": 18264834,
                        "generate": 355382
                    },
                    "time": 19097043
                },
                "apply": {
                    "components": {
                        "simple_apply": 42233
                    },
                    "time": 38052
                },
                "completed": true
            },
            "jacobi-19": {
                "generate": {
                    "components": {
                        "find_blocks": 18337193,
                        "generate": 367056
                    },
                    "time": 19204221
                },
                "apply": {
                    "components": {
                        "simple_apply": 43487
                    },
                    "time": 38292
                },
                "completed": true
            },
            "jacobi-20": {
                "generate": {
                    "components": {
                        "find_blocks": 18260083,
                        "generate": 395172
                    },
                    "time": 19132756
                },
                "apply": {
                    "components": {
                        "simple_apply": 42662
                    },
                    "time": 38242
                },
                "completed": true
            },
            "jacobi-21": {
                "generate": {
                    "components": {
                        "find_blocks": 18316136,
                        "generate": 412786
                    },
                    "time": 19233987
                },
                "apply": {
                    "components": {
                        "simple_apply": 43553
                    },
                    "time": 38457
                },
                "completed": true
            },
            "jacobi-22": {
                "generate": {
                    "components": {
                        "find_blocks": 18254986,
                        "generate": 426882
                    },
                    "time": 19146939
                },
                "apply": {
                    "components": {
                        "simple_apply": 41368
                    },
                    "time": 36691
                },
                "completed": true
            },
            "jacobi-23": {
                "generate": {
                    "components": {
                        "find_blocks": 18327316,
                        "generate": 446766
                    },
                    "time": 19267102
                },
                "apply": {
                    "components": {
                        "simple_apply": 40761
                    },
                    "time": 35685
                },
                "completed": true
            },
            "jacobi-24": {
                "generate": {
                    "components": {
                        "find_blocks": 18280401,
                        "generate": 462070
                    },
                    "time": 19221673
                },
                "apply": {
                    "components": {
                        "simple_apply": 40242
                    },
                    "time": 35976
                },
                "completed": true
            },
            "jacobi-25": {
                "generate": {
                    "components": {
                        "find_blocks": 18326909,
                        "generate": 476226
                    },
                    "time": 19276129
                },
                "apply": {
                    "components": {
                        "simple_apply": 44003
                    },
                    "time": 39315
                },
                "completed": true
            },
            "jacobi-26": {
                "generate": {
                    "components": {
                        "find_blocks": 18270550,
                        "generate": 507599
                    },
                    "time": 19244194
                },
                "apply": {
                    "components": {
                        "simple_apply": 44045
                    },
                    "time": 40096
                },
                "completed": true
            },
            "jacobi-27": {
                "generate": {
                    "components": {
                        "find_blocks": 18310402,
                        "generate": 521459
                    },
                    "time": 19323178
                },
                "apply": {
                    "components": {
                        "simple_apply": 45774
                    },
                    "time": 41043
                },
                "completed": true
            },
            "jacobi-28": {
                "generate": {
                    "components": {
                        "find_blocks": 18256341,
                        "generate": 500029
                    },
                    "time": 19225996
                },
                "apply": {
                    "components": {
                        "simple_apply": 44207
                    },
                    "time": 39892
                },
                "completed": true
            },
            "jacobi-29": {
                "generate": {
                    "components": {
                        "find_blocks": 18301479,
                        "generate": 544831
                    },
                    "time": 19336876
                },
                "apply": {
                    "components": {
                        "simple_apply": 45108
                    },
                    "time": 40371
                },
                "completed": true
            },
            "jacobi-30": {
                "generate": {
                    "components": {
                        "find_blocks": 18249519,
                        "generate": 592379
                    },
                    "time": 19312482
                },
                "apply": {
                    "components": {
                        "simple_apply": 49018
                    },
                    "time": 45392
                },
                "completed": true
            },
            "jacobi-31": {
                "generate": {
                    "components": {
                        "find_blocks": 18308709,
                        "generate": 598741
                    },
                    "time": 19403931
                },
                "apply": {
                    "components": {
                        "simple_apply": 52838
                    },
                    "time": 49904
                },
                "completed": true
            },
            "jacobi-32": {
                "generate": {
                    "components": {
                        "find_blocks": 18281430,
                        "generate": 689870
                    },
                    "time": 19422249
                },
                "apply": {
                    "components": {
                        "simple_apply": 48300
                    },
                    "time": 44704
                },
                "completed": true
            }
        }
    }
]