[
    {
        "filename": "/tmp/block-diagonal/18000-14.mtx",
        "problem": {
            "type": "block-diagonal",
            "num_blocks": 18000,
            "block_size": 14,
            "row_distribution": {
                "min": 14,
                "q1": 14.0,
                "median": 14.0,
                "q3": 14.0,
                "max": 14,
                "mean": 14.0,
                "variance": 0.0,
                "skewness": 0.0,
                "kurtosis": 0.0,
                "hyperskewness": 0.0,
                "hyperflatness": 0.0
            },
            "col_distribution": {
                "min": 14,
                "q1": 14.0,
                "median": 14.0,
                "q3": 14.0,
                "max": 14,
                "mean": 14.0,
                "variance": 0.0,
                "skewness": 0.0,
                "kurtosis": 0.0,
                "hyperskewness": 0.0,
                "hyperflatness": 0.0
            }
        },
        "preconditioner": {
            "jacobi-1": {
                "generate": {
                    "components": {
                        "find_blocks": 127098066,
                        "generate": 235007
                    },
                    "time": 127562062
                },
                "apply": {
                    "components": {
                        "simple_apply": 25368
                    },
                    "time": 17276
                },
                "completed": true
            },
            "jacobi-2": {
                "generate": {
                    "components": {
                        "find_blocks": 73673039,
                        "generate": 477037
                    },
                    "time": 74610566
                },
                "apply": {
                    "components": {
                        "simple_apply": 70275
                    },
                    "time": 61740
                },
                "completed": true
            },
            "jacobi-3": {
                "generate": {
                    "components": {
                        "find_blocks": 59206286,
                        "generate": 506829
                    },
                    "time": 60318740
                },
                "apply": {
                    "components": {
                        "simple_apply": 66928
                    },
                    "time": 58306
                },
                "completed": true
            },
            "jacobi-4": {
                "generate": {
                    "components": {
                        "find_blocks": 51513148,
                        "generate": 537860
                    },
                    "time": 53034187
                },
                "apply": {
                    "components": {
                        "simple_apply": 67047
                    },
                    "time": 59164
                },
                "completed": true
            },
            "jacobi-5": {
                "generate": {
                    "components": {
                        "find_blocks": 44215838,
                        "generate": 525227
                    },
                    "time": 46442459
                },
                "apply": {
                    "components": {
                        "simple_apply": 64021
                    },
                    "time": 56426
                },
                "completed": true
            },
            "jacobi-6": {
                "generate": {
                    "components": {
                        "find_blocks": 43981225,
                        "generate": 612124
                    },
                    "time": 45544283
                },
                "apply": {
                    "components": {
                        "simple_apply": 72427
                    },
                    "time": 64385
                },
                "completed": true
            },
            "jacobi-7": {
                "generate": {
                    "components": {
                        "find_blocks": 36665965,
                        "generate": 520765
                    },
                    "time": 38615537
                },
                "apply": {
                    "components": {
                        "simple_apply": 65276
                    },
                    "time": 58213
                },
                "completed": true
            },
            "jacobi-8": {
                "generate": {
                    "components": {
                        "find_blocks": 36525366,
                        "generate": 569087
                    },
                    "time": 38688453
                },
                "apply": {
                    "components": {
                        "simple_apply": 70662
                    },
                    "time": 63067
                },
                "completed": true
            },
            "jacobi-9": {
                "generate": {
                    "components": {
                        "find_blocks": 36666477,
                        "generate": 615945
                    },
                    "time": 38770082
                },
                "apply": {
                    "components": {
                        "simple_apply": 77591
                    },
                    "time": 71158
                },
                "completed": true
            },
            "jacobi-10": {
                "generate": {
                    "components": {
                        "find_blocks": 36525393,
                        "generate": 664881
                    },
                    "time": 38690564
                },
                "apply": {
                    "components": {
                        "simple_apply": 80331
                    },
                    "time": 73911
                },
                "completed": true
            },
            "jacobi-11": {
                "generate": {
                    "components": {
                        "find_blocks": 36674090,
                        "generate": 718304
                    },
                    "time": 38817068
                },
                "apply": {
                    "components": {
                        "simple_apply": 86662
                    },
                    "time": 80401
                },
                "completed": true
            },
            "jacobi-12": {
                "generate": {
                    "components": {
                        "find_blocks": 36501174,
                        "generate": 774411
                    },
                    "time": 39163145
                },
                "apply": {
                    "components": {
                        "simple_apply": 91730
                    },
                    "time": 84720
                },
                "completed": true
            },
            "jacobi-13": {
                "generate": {
                    "components": {
                        "find_blocks": 36681102,
                        "generate": 729977
                    },
                    "time": 39281059
                },
                "apply": {
                    "components": {
                        "simple_apply": 100142
                    },
                    "time": 92864
                },
                "completed": true
            },
            "jacobi-14": {
                "generate": {
                    "components": {
                        "find_blocks": 28996658,
                        "generate": 627836
                    },
                    "time": 31617253
                },
                "apply": {
                    "components": {
                        "simple_apply": 95126
                    },
                    "time": 87957
                },
                "completed": true
            },
            "jacobi-15": {
                "generate": {
                    "components": {
                        "find_blocks": 28957856,
                        "generate": 642509
                    },
                    "time": 31777187
                },
                "apply": {
                    "components": {
                        "simple_apply": 98565
                    },
                    "time": 92024
                },
                "completed": true
            },
            "jacobi-16": {
                "generate": {
                    "components": {
                        "find_blocks": 29040611,
                        "generate": 645078
                    },
                    "time": 31558316
                },
                "apply": {
                    "components": {
                        "simple_apply": 94816
                    },
                    "time": 88171
                },
                "completed": true
            },
            "jacobi-17": {
                "generate": {
                    "components": {
                        "find_blocks": 29013429,
                        "generate": 1292977
                    },
                    "time": 32180267
                },
                "apply": {
                    "components": {
                        "simple_apply": 113319
                    },
                    "time": 104925
                },
                "completed": true
            },
            "jacobi-18": {
                "generate": {
                    "components": {
                        "find_blocks": 28979148,
                        "generate": 1287394
                    },
                    "time": 32263627
                },
                "apply": {
                    "components": {
                        "simple_apply": 113103
                    },
                    "time": 105442
                },
                "completed": true
            },
            "jacobi-19": {
                "generate": {
                    "components": {
                        "find_blocks": 29020731,
                        "generate": 1294487
                    },
                    "time": 32426130
                },
                "apply": {
                    "components": {
                        "simple_apply": 113104
                    },
                    "time": 105069
                },
                "completed": true
            },
            "jacobi-20": {
                "generate": {
                    "components": {
                        "find_blocks": 28986867,
                        "generate": 1296107
                    },
                    "time": 32602461
                },
                "apply": {
                    "components": {
                        "simple_apply": 112534
                    },
                    "time": 104185
                },
                "completed": true
            },
            "jacobi-21": {
                "generate": {
                    "components": {
                        "find_blocks": 28959030,
                        "generate": 1296044
                    },
                    "time": 32898180
                },
                "apply": {
                    "components": {
                        "simple_apply": 114621
                    },
                    "time": 106195
                },
                "completed": true
            },
            "jacobi-22": {
                "generate": {
                    "components": {
                        "find_blocks": 29008834,
                        "generate": 1293684
                    },
                    "time": 32969406
                },
                "apply": {
                    "components": {
                        "simple_apply": 113582
                    },
                    "time": 104746
                },
                "completed": true
            },
            "jacobi-23": {
                "generate": {
                    "components": {
                        "find_blocks": 29635589,
                        "generate": 1300105
                    },
                    "time": 33010201
                },
                "apply": {
                    "components": {
                        "simple_apply": 114199
                    },
                    "time": 106178
                },
                "completed": true
            },
            "jacobi-24": {
                "generate": {
                    "components": {
                        "find_blocks": 28983647,
                        "generate": 1297883
                    },
                    "time": 32858352
                },
                "apply": {
                    "components": {
                        "simple_apply": 114273
                    },
                    "time": 104959
                },
                "completed": true
            },
            "jacobi-25": {
                "generate": {
                    "components": {
                        "find_blocks": 28992129,
                        "generate": 1300194
                    },
                    "time": 33209365
                },
                "apply": {
                    "components": {
                        "simple_apply": 116194
                    },
                    "time": 107169
                },
                "completed": true
            },
            "jacobi-26": {
                "generate": {
                    "components": {
                        "find_blocks": 29000805,
                        "generate": 1301570
                    },
                    "time": 32978041
                },
                "apply": {
                    "components": {
                        "simple_apply": 116423
                    },
                    "time": 105970
                },
                "completed": true
            },
            "jacobi-27": {
                "generate": {
                    "components": {
                        "find_blocks": 28984339,
                        "generate": 1309714
                    },
                    "time": 32861208
                },
                "apply": {
                    "components": {
                        "simple_apply": 115982
                    },
                    "time": 107490
                },
                "completed": true
            },
            "jacobi-28": {
                "generate": {
                    "components": {
                        "find_blocks": 27245668,
                        "generate": 1423454
                    },
                    "time": 31188766
                },
                "apply": {
                    "components": {
                        "simple_apply": 158336
                    },
                    "time": 150871
                },
                "completed": true
            },
            "jacobi-29": {
                "generate": {
                    "components": {
                        "find_blocks": 27249472,
                        "generate": 1436597
                    },
                    "time": 31617501
                },
                "apply": {
                    "components": {
                        "simple_apply": 159996
                    },
                    "time": 151975
                },
                "completed": true
            },
            "jacobi-30": {
                "generate": {
                    "components": {
                        "find_blocks": 27238620,
                        "generate": 1441776
                    },
                    "time": 31327855
                },
                "apply": {
                    "components": {
                        "simple_apply": 165529
                    },
                    "time": 158893
                },
                "completed": true
            },
            "jacobi-31": {
                "generate": {
                    "components": {
                        "find_blocks": 27208786,
                        "generate": 1438517
                    },
                    "time": 31490843
                },
                "apply": {
                    "components": {
                        "simple_apply": 170601
                    },
                    "time": 164203
                },
                "completed": true
            },
            "jacobi-32": {
                "generate": {
                    "components": {
                        "find_blocks": 27268902,
                        "generate": 1420278
                    },
                    "time": 31509909
                },
                "apply": {
                    "components": {
                        "simple_apply": 152586
                    },
                    "time": 142647
                },
                "completed": true
            }
        }
    }
]